PyDesmos
