Metadata-Version: 2.1
Name: PyDesmos
Version: 0.1.2
Summary: An easy-to-use Python to Desmos graph HTML compiler via the Desmos API (with OEIS support).
Home-page: 
Author: Lyam Boylan
Author-email: lyamboylan@gmail.com
License: MIT
Keywords: math,graph,desmos,graphing software,html,sympy,api,oeis
Classifier: Development Status :: 3 - Alpha
Classifier: Intended Audience :: Education
Classifier: Operating System :: Microsoft :: Windows :: Windows 10
Classifier: License :: OSI Approved :: MIT License
Classifier: Programming Language :: Python :: 3
License-File: LICENSE.txt
